sensor_dataset/__init__.py
sensor_dataset/_nbdev.py
sensor_dataset/outlier_detection.py
sensor_dataset-0.0.1.dist-info/LICENSE
sensor_dataset-0.0.1.dist-info/METADATA
sensor_dataset-0.0.1.dist-info/WHEEL
sensor_dataset-0.0.1.dist-info/entry_points.txt
sensor_dataset-0.0.1.dist-info/top_level.txt
sensor_dataset-0.0.1.dist-info/RECORD
