Metadata-Version: 2.1
Name: sensor-dataset
Version: 0.0.1
Summary: Put a description
Home-page: https://github.com/kikejimenez/sensor_dataset/tree/master/
Author: Enrique Jimenez
Author-email: physieira@gmail.com
License: Apache Software License 2.0
Keywords: outlier detection statistics
Platform: UNKNOWN
Classifier: Development Status :: 3 - Alpha
Classifier: Intended Audience :: Developers
Classifier: Natural Language :: English
Classifier: Programming Language :: Python :: 3.6
Classifier: Programming Language :: Python :: 3.7
Classifier: Programming Language :: Python :: 3.8
Classifier: License :: OSI Approved :: Apache Software License
Requires-Python: >=3.6
Requires-Dist: pip
Requires-Dist: packaging
Requires-Dist: pandas
Requires-Dist: plotly
Requires-Dist: scipy
Requires-Dist: koalas
Requires-Dist: pyspark
Requires-Dist: py4j
Requires-Dist: kaleido
Provides-Extra: dev
